MANIFEST.in
README.md
setup.py
my_cge_cc.egg-info/PKG-INFO
my_cge_cc.egg-info/SOURCES.txt
my_cge_cc.egg-info/dependency_links.txt
my_cge_cc.egg-info/top_level.txt
new_project_pyp/__init__.py
new_project_pyp/module.py