Metadata-Version: 2.1
Name: my-cge-cc
Version: 1.0
Summary: Super Liberary
Author: Gargamel
